{
  "Lepton@1.4.3-alpha": {
    "licenses": "MIT",
    "repository": "https://github.com/hackjutsu/Lepton",
    "publisher": "CosmoX",
    "licenseFile": "LICENSE"
  },
  "agent-base@2.1.1": {
    "licenses": "MIT",
    "repository": "https://github.com/TooTallNate/node-agent-base",
    "publisher": "Nathan Rajlich",
    "email": "nathan@tootallnate.net",
    "url": "http://n8.io/",
    "licenseFile": "node_modules/agent-base/README.md"
  },
  "agent-base@4.1.1": {
    "licenses": "MIT",
    "repository": "https://github.com/TooTallNate/node-agent-base",
    "publisher": "Nathan Rajlich",
    "email": "nathan@tootallnate.net",
    "url": "http://n8.io/",
    "licenseFile": "node_modules/pac-proxy-agent/node_modules/socks-proxy-agent/node_modules/agent-base/README.md"
  },
  "ajv@4.11.8": {
    "licenses": "MIT",
    "repository": "https://github.com/epoberezkin/ajv",
    "publisher": "Evgeny Poberezkin",
    "licenseFile": "node_modules/ajv/LICENSE"
  },
  "amdefine@1.0.1": {
    "licenses": "BSD-3-Clause OR MIT",
    "repository": "https://github.com/jrburke/amdefine",
    "publisher": "James Burke",
    "email": "jrburke@gmail.com",
    "url": "http://github.com/jrburke",
    "licenseFile": "node_modules/amdefine/LICENSE"
  },
  "ansi-regex@2.1.1": {
    "licenses": "MIT",
    "repository": "https://github.com/chalk/ansi-regex",
    "publisher": "Sindre Sorhus",
    "email": "sindresorhus@gmail.com",
    "url": "sindresorhus.com",
    "licenseFile": "node_modules/ansi-regex/license"
  },
  "argparse@1.0.9": {
    "licenses": "MIT",
    "repository": "https://github.com/nodeca/argparse",
    "licenseFile": "node_modules/argparse/LICENSE"
  },
  "asap@2.0.5": {
    "licenses": "MIT",
    "repository": "https://github.com/kriskowal/asap",
    "licenseFile": "node_modules/asap/LICENSE.md"
  },
  "asn1@0.2.3": {
    "licenses": "MIT",
    "repository": "https://github.com/mcavage/node-asn1",
    "publisher": "Mark Cavage",
    "email": "mcavage@gmail.com",
    "licenseFile": "node_modules/asn1/LICENSE"
  },
  "assert-plus@0.2.0": {
    "licenses": "MIT",
    "repository": "https://github.com/mcavage/node-assert-plus",
    "publisher": "Mark Cavage",
    "email": "mcavage@gmail.com",
    "licenseFile": "node_modules/assert-plus/README.md"
  },
  "assert-plus@1.0.0": {
    "licenses": "MIT",
    "repository": "https://github.com/mcavage/node-assert-plus",
    "publisher": "Mark Cavage",
    "email": "mcavage@gmail.com",
    "licenseFile": "node_modules/jsprim/node_modules/assert-plus/README.md"
  },
  "ast-types@0.9.6": {
    "licenses": "MIT",
    "repository": "https://github.com/benjamn/ast-types",
    "publisher": "Ben Newman",
    "email": "bn@cs.stanford.edu",
    "licenseFile": "node_modules/ast-types/LICENSE"
  },
  "async@1.0.0": {
    "licenses": "MIT",
    "repository": "https://github.com/caolan/async",
    "publisher": "Caolan McMahon",
    "licenseFile": "node_modules/async/LICENSE"
  },
  "async@1.5.2": {
    "licenses": "MIT",
    "repository": "https://github.com/caolan/async",
    "publisher": "Caolan McMahon",
    "licenseFile": "node_modules/nconf/node_modules/async/LICENSE"
  },
  "asynckit@0.4.0": {
    "licenses": "MIT",
    "repository": "https://github.com/alexindigo/asynckit",
    "publisher": "Alex Indigo",
    "email": "iam@alexindigo.com",
    "licenseFile": "node_modules/asynckit/LICENSE"
  },
  "autolinker@1.4.3": {
    "licenses": "MIT",
    "repository": "https://github.com/gregjacobs/Autolinker.js",
    "publisher": "Gregory Jacobs",
    "email": "greg@greg-jacobs.com",
    "licenseFile": "node_modules/autolinker/LICENSE"
  },
  "aws-sign2@0.6.0": {
    "licenses": "Apache-2.0",
    "repository": "https://github.com/mikeal/aws-sign",
    "publisher": "Mikeal Rogers",
    "email": "mikeal.rogers@gmail.com",
    "url": "http://www.futurealoof.com",
    "licenseFile": "node_modules/aws-sign2/LICENSE"
  },
  "aws4@1.6.0": {
    "licenses": "MIT",
    "repository": "https://github.com/mhart/aws4",
    "publisher": "Michael Hart",
    "email": "michael.hart.au@gmail.com",
    "url": "http://github.com/mhart",
    "licenseFile": "node_modules/aws4/LICENSE"
  },
  "babel-runtime@6.23.0": {
    "licenses": "MIT",
    "repository": "https://github.com/babel/babel/tree/master/packages/babel-runtime",
    "publisher": "Sebastian McKenzie",
    "email": "sebmck@gmail.com",
    "licenseFile": "node_modules/babel-runtime/README.md"
  },
  "bcrypt-pbkdf@1.0.1": {
    "licenses": "BSD-3-Clause",
    "licenseFile": "node_modules/bcrypt-pbkdf/README.md"
  },
  "bluebird-lst@1.0.3": {
    "licenses": "MIT",
    "repository": "https://github.com/develar/fs-extra-p",
    "publisher": "Vladimir Krivosheev"
  },
  "bluebird@3.5.0": {
    "licenses": "MIT",
    "repository": "https://github.com/petkaantonov/bluebird",
    "publisher": "Petka Antonov",
    "email": "petka_antonov@hotmail.com",
    "url": "http://github.com/petkaantonov/",
    "licenseFile": "node_modules/bluebird/LICENSE"
  },
  "boom@2.10.1": {
    "licenses": "BSD-3-Clause",
    "repository": "https://github.com/hapijs/boom",
    "licenseFile": "node_modules/boom/LICENSE"
  },
  "bowser@1.7.1": {
    "licenses": "MIT",
    "repository": "https://github.com/ded/bowser",
    "publisher": "Dustin Diaz",
    "email": "dustin@dustindiaz.com",
    "url": "http://dustindiaz.com",
    "licenseFile": "node_modules/bowser/LICENSE"
  },
  "builder-util-runtime@1.0.1": {
    "licenses": "MIT",
    "repository": "https://github.com/electron-userland/electron-builder",
    "publisher": "Vladimir Krivosheev",
    "licenseFile": "node_modules/builder-util-runtime/readme.md"
  },
  "bytes@2.5.0": {
    "licenses": "MIT",
    "repository": "https://github.com/visionmedia/bytes.js",
    "publisher": "TJ Holowaychuk",
    "email": "tj@vision-media.ca",
    "url": "http://tjholowaychuk.com",
    "licenseFile": "node_modules/bytes/LICENSE"
  },
  "camelcase@2.1.1": {
    "licenses": "MIT",
    "repository": "https://github.com/sindresorhus/camelcase",
    "publisher": "Sindre Sorhus",
    "email": "sindresorhus@gmail.com",
    "url": "http://sindresorhus.com",
    "licenseFile": "node_modules/camelcase/license"
  },
  "caseless@0.12.0": {
    "licenses": "Apache-2.0",
    "repository": "https://github.com/mikeal/caseless",
    "publisher": "Mikeal Rogers",
    "email": "mikeal.rogers@gmail.com",
    "licenseFile": "node_modules/caseless/LICENSE"
  },
  "classnames@2.2.5": {
    "licenses": "MIT",
    "repository": "https://github.com/JedWatson/classnames",
    "publisher": "Jed Watson",
    "licenseFile": "node_modules/classnames/LICENSE"
  },
  "cliui@3.2.0": {
    "licenses": "ISC",
    "repository": "https://github.com/yargs/cliui",
    "publisher": "Ben Coe",
    "email": "ben@npmjs.com",
    "licenseFile": "node_modules/cliui/LICENSE.txt"
  },
  "co@4.6.0": {
    "licenses": "MIT",
    "repository": "https://github.com/tj/co",
    "licenseFile": "node_modules/co/LICENSE"
  },
  "code-point-at@1.1.0": {
    "licenses": "MIT",
    "repository": "https://github.com/sindresorhus/code-point-at",
    "publisher": "Sindre Sorhus",
    "email": "sindresorhus@gmail.com",
    "url": "sindresorhus.com",
    "licenseFile": "node_modules/code-point-at/license"
  },
  "codemirror@5.28.0": {
    "licenses": "MIT",
    "repository": "https://github.com/codemirror/CodeMirror",
    "licenseFile": "node_modules/codemirror/LICENSE"
  },
  "colors@1.0.3": {
    "licenses": "MIT",
    "repository": "https://github.com/Marak/colors.js",
    "publisher": "Marak Squires",
    "licenseFile": "node_modules/colors/ReadMe.md"
  },
  "combined-stream@1.0.5": {
    "licenses": "MIT",
    "repository": "https://github.com/felixge/node-combined-stream",
    "publisher": "Felix Geisendörfer",
    "email": "felix@debuggable.com",
    "url": "http://debuggable.com/",
    "licenseFile": "node_modules/combined-stream/License"
  },
  "core-js@1.2.7": {
    "licenses": "MIT",
    "repository": "https://github.com/zloirock/core-js",
    "licenseFile": "node_modules/core-js/LICENSE"
  },
  "core-js@2.4.1": {
    "licenses": "MIT",
    "repository": "https://github.com/zloirock/core-js",
    "licenseFile": "node_modules/babel-runtime/node_modules/core-js/LICENSE"
  },
  "core-util-is@1.0.2": {
    "licenses": "MIT",
    "repository": "https://github.com/isaacs/core-util-is",
    "publisher": "Isaac Z. Schlueter",
    "email": "i@izs.me",
    "url": "http://blog.izs.me/",
    "licenseFile": "node_modules/core-util-is/LICENSE"
  },
  "create-react-class@15.6.0": {
    "licenses": "BSD-3-Clause",
    "repository": "https://github.com/facebook/react",
    "licenseFile": "node_modules/create-react-class/LICENSE.txt"
  },
  "cryptiles@2.0.5": {
    "licenses": "BSD-3-Clause",
    "repository": "https://github.com/hapijs/cryptiles",
    "licenseFile": "node_modules/cryptiles/LICENSE"
  },
  "css-in-js-utils@1.0.3": {
    "licenses": "MIT",
    "repository": "https://github.com/rofrischmann/css-in-js-utils",
    "publisher": "Robin Frischmann",
    "email": "robin@rofrischmann.de",
    "licenseFile": "node_modules/css-in-js-utils/LICENSE"
  },
  "cycle@1.0.3": {
    "licenses": "Custom: https://github.com/douglascrockford/JSON-js",
    "repository": "https://github.com/dscape/cycle",
    "licenseFile": "node_modules/cycle/README.md"
  },
  "dashdash@1.14.1": {
    "licenses": "MIT",
    "repository": "https://github.com/trentm/node-dashdash",
    "publisher": "Trent Mick",
    "email": "trentm@gmail.com",
    "url": "http://trentm.com",
    "licenseFile": "node_modules/dashdash/LICENSE.txt"
  },
  "data-uri-to-buffer@1.2.0": {
    "licenses": "MIT",
    "repository": "https://github.com/TooTallNate/node-data-uri-to-buffer",
    "publisher": "Nathan Rajlich",
    "email": "nathan@tootallnate.net",
    "url": "http://n8.io/",
    "licenseFile": "node_modules/data-uri-to-buffer/README.md"
  },
  "debug@2.6.8": {
    "licenses": "MIT",
    "repository": "https://github.com/visionmedia/debug",
    "publisher": "TJ Holowaychuk",
    "email": "tj@vision-media.ca",
    "licenseFile": "node_modules/debug/LICENSE"
  },
  "debug@3.0.1": {
    "licenses": "MIT",
    "repository": "https://github.com/visionmedia/debug",
    "publisher": "TJ Holowaychuk",
    "email": "tj@vision-media.ca",
    "licenseFile": "node_modules/builder-util-runtime/node_modules/debug/LICENSE"
  },
  "decamelize@1.2.0": {
    "licenses": "MIT",
    "repository": "https://github.com/sindresorhus/decamelize",
    "publisher": "Sindre Sorhus",
    "email": "sindresorhus@gmail.com",
    "url": "sindresorhus.com",
    "licenseFile": "node_modules/decamelize/license"
  },
  "deep-equal@1.0.1": {
    "licenses": "MIT",
    "repository": "https://github.com/substack/node-deep-equal",
    "publisher": "James Halliday",
    "email": "mail@substack.net",
    "url": "http://substack.net",
    "licenseFile": "node_modules/deep-equal/LICENSE"
  },
  "deep-is@0.1.3": {
    "licenses": "MIT",
    "repository": "https://github.com/thlorenz/deep-is",
    "publisher": "Thorsten Lorenz",
    "email": "thlorenz@gmx.de",
    "url": "http://thlorenz.com",
    "licenseFile": "node_modules/deep-is/LICENSE"
  },
  "degenerator@1.0.4": {
    "licenses": "MIT",
    "repository": "https://github.com/TooTallNate/node-degenerator",
    "publisher": "Nathan Rajlich",
    "email": "nathan@tootallnate.net",
    "url": "http://n8.io/",
    "licenseFile": "node_modules/degenerator/README.md"
  },
  "delayed-stream@1.0.0": {
    "licenses": "MIT",
    "repository": "https://github.com/felixge/node-delayed-stream",
    "publisher": "Felix Geisendörfer",
    "email": "felix@debuggable.com",
    "url": "http://debuggable.com/",
    "licenseFile": "node_modules/delayed-stream/License"
  },
  "depd@1.1.0": {
    "licenses": "MIT",
    "repository": "https://github.com/dougwilson/nodejs-depd",
    "publisher": "Douglas Christopher Wilson",
    "email": "doug@somethingdoug.com",
    "licenseFile": "node_modules/depd/LICENSE"
  },
  "dom-helpers@3.2.1": {
    "licenses": "MIT",
    "repository": "https://github.com/jquense/dom-helpers",
    "publisher": "Jason Quense",
    "email": "monastic.panic@gmail.com",
    "licenseFile": "node_modules/dom-helpers/README.md"
  },
  "ecc-jsbn@0.1.1": {
    "licenses": "MIT",
    "repository": "https://github.com/quartzjer/ecc-jsbn",
    "publisher": "Jeremie Miller",
    "email": "jeremie@jabber.org",
    "url": "http://jeremie.com/",
    "licenseFile": "node_modules/ecc-jsbn/LICENSE"
  },
  "electron-context-menu@0.9.1": {
    "licenses": "MIT",
    "repository": "https://github.com/sindresorhus/electron-context-menu",
    "publisher": "Sindre Sorhus",
    "email": "sindresorhus@gmail.com",
    "url": "sindresorhus.com",
    "licenseFile": "node_modules/electron-context-menu/license"
  },
  "electron-dl@1.9.0": {
    "licenses": "MIT",
    "repository": "https://github.com/sindresorhus/electron-dl",
    "publisher": "Sindre Sorhus",
    "email": "sindresorhus@gmail.com",
    "url": "sindresorhus.com",
    "licenseFile": "node_modules/electron-dl/license"
  },
  "electron-is-accelerator@0.1.2": {
    "licenses": "MIT",
    "repository": "https://github.com/brrd/electron-is-accelerator",
    "publisher": "brrd",
    "licenseFile": "node_modules/electron-is-accelerator/LICENSE"
  },
  "electron-is-dev@0.1.2": {
    "licenses": "MIT",
    "repository": "https://github.com/sindresorhus/electron-is-dev",
    "publisher": "Sindre Sorhus",
    "email": "sindresorhus@gmail.com",
    "url": "sindresorhus.com",
    "licenseFile": "node_modules/electron-context-menu/node_modules/electron-is-dev/license"
  },
  "electron-is-dev@0.3.0": {
    "licenses": "MIT",
    "repository": "https://github.com/sindresorhus/electron-is-dev",
    "publisher": "Sindre Sorhus",
    "email": "sindresorhus@gmail.com",
    "url": "sindresorhus.com",
    "licenseFile": "node_modules/electron-is-dev/license"
  },
  "electron-localshortcut@3.0.2": {
    "licenses": "MIT",
    "repository": "https://github.com/parro-it/electron-localshortcut",
    "publisher": "andrea@parro.it",
    "licenseFile": "node_modules/electron-localshortcut/license"
  },
  "electron-updater@2.9.3": {
    "licenses": "MIT",
    "repository": "https://github.com/electron-userland/electron-builder",
    "publisher": "Vladimir Krivosheev",
    "licenseFile": "node_modules/electron-updater/README.md"
  },
  "electron-window-state@4.1.1": {
    "licenses": "MIT",
    "repository": "https://github.com/mawie81/electron-window-state",
    "publisher": "Marcel Wiehle",
    "licenseFile": "node_modules/electron-window-state/license"
  },
  "encoding@0.1.12": {
    "licenses": "MIT",
    "repository": "https://github.com/andris9/encoding",
    "publisher": "Andris Reinman",
    "licenseFile": "node_modules/encoding/LICENSE"
  },
  "entities@1.1.1": {
    "licenses": "BSD*",
    "repository": "https://github.com/fb55/node-entities",
    "publisher": "Felix Boehm",
    "email": "me@feedic.com",
    "licenseFile": "node_modules/entities/LICENSE"
  },
  "es6-error@4.0.2": {
    "licenses": "MIT",
    "repository": "https://github.com/bjyoungblood/es6-error",
    "publisher": "Ben Youngblood",
    "licenseFile": "node_modules/es6-error/LICENSE.md"
  },
  "es6-promise@4.1.1": {
    "licenses": "MIT",
    "repository": "https://github.com/stefanpenner/es6-promise",
    "publisher": "Yehuda Katz, Tom Dale, Stefan Penner and contributors",
    "url": "Conversion to ES6 API by Jake Archibald",
    "licenseFile": "node_modules/es6-promise/LICENSE"
  },
  "es6-promisify@5.0.0": {
    "licenses": "MIT",
    "repository": "https://github.com/digitaldesignlabs/es6-promisify",
    "publisher": "Mike Hall",
    "email": "mikehall314@gmail.com",
    "licenseFile": "node_modules/es6-promisify/README.md"
  },
  "escodegen@1.8.1": {
    "licenses": "BSD-2-Clause",
    "repository": "https://github.com/estools/escodegen",
    "licenseFile": "node_modules/escodegen/LICENSE.BSD"
  },
  "esprima@2.7.3": {
    "licenses": "BSD-2-Clause",
    "repository": "https://github.com/jquery/esprima",
    "publisher": "Ariya Hidayat",
    "email": "ariya.hidayat@gmail.com",
    "licenseFile": "node_modules/escodegen/node_modules/esprima/LICENSE.BSD"
  },
  "esprima@3.1.3": {
    "licenses": "BSD-2-Clause",
    "repository": "https://github.com/jquery/esprima",
    "publisher": "Ariya Hidayat",
    "email": "ariya.hidayat@gmail.com",
    "licenseFile": "node_modules/esprima/LICENSE.BSD"
  },
  "esprima@4.0.0": {
    "licenses": "BSD-2-Clause",
    "repository": "https://github.com/jquery/esprima",
    "publisher": "Ariya Hidayat",
    "email": "ariya.hidayat@gmail.com",
    "licenseFile": "node_modules/electron-updater/node_modules/esprima/LICENSE.BSD"
  },
  "estraverse@1.9.3": {
    "licenses": "BSD",
    "repository": "https://github.com/estools/estraverse",
    "licenseFile": "node_modules/escodegen/node_modules/estraverse/LICENSE.BSD"
  },
  "esutils@2.0.2": {
    "licenses": "BSD",
    "repository": "https://github.com/estools/esutils",
    "licenseFile": "node_modules/esutils/LICENSE.BSD"
  },
  "extend@3.0.1": {
    "licenses": "MIT",
    "repository": "https://github.com/justmoon/node-extend",
    "publisher": "Stefan Thomas",
    "email": "justmoon@members.fsf.org",
    "url": "http://www.justmoon.net",
    "licenseFile": "node_modules/extend/LICENSE"
  },
  "extsprintf@1.0.2": {
    "licenses": "MIT*",
    "repository": "https://github.com/davepacheco/node-extsprintf",
    "licenseFile": "node_modules/extsprintf/LICENSE"
  },
  "eyes@0.1.8": {
    "licenses": "MIT",
    "publisher": "Alexis Sellier",
    "email": "self@cloudhead.net",
    "licenseFile": "node_modules/eyes/LICENSE"
  },
  "fast-levenshtein@2.0.6": {
    "licenses": "MIT",
    "repository": "https://github.com/hiddentao/fast-levenshtein",
    "publisher": "Ramesh Nair",
    "email": "ram@hiddentao.com",
    "url": "http://www.hiddentao.com/",
    "licenseFile": "node_modules/fast-levenshtein/LICENSE.md"
  },
  "fbjs@0.8.12": {
    "licenses": "BSD-3-Clause",
    "repository": "https://github.com/facebook/fbjs",
    "licenseFile": "node_modules/fbjs/LICENSE"
  },
  "file-uri-to-path@1.0.0": {
    "licenses": "MIT",
    "repository": "https://github.com/TooTallNate/file-uri-to-path",
    "publisher": "Nathan Rajlich",
    "email": "nathan@tootallnate.net",
    "url": "http://n8.io/",
    "licenseFile": "node_modules/file-uri-to-path/LICENSE"
  },
  "forever-agent@0.6.1": {
    "licenses": "Apache-2.0",
    "repository": "https://github.com/mikeal/forever-agent",
    "publisher": "Mikeal Rogers",
    "email": "mikeal.rogers@gmail.com",
    "url": "http://www.futurealoof.com",
    "licenseFile": "node_modules/forever-agent/LICENSE"
  },
  "form-data@2.1.4": {
    "licenses": "MIT",
    "repository": "https://github.com/form-data/form-data",
    "publisher": "Felix Geisendörfer",
    "email": "felix@debuggable.com",
    "url": "http://debuggable.com/",
    "licenseFile": "node_modules/form-data/License"
  },
  "fs-extra-p@4.4.0": {
    "licenses": "MIT",
    "repository": "https://github.com/develar/fs-extra-p",
    "licenseFile": "node_modules/builder-util-runtime/node_modules/fs-extra-p/LICENSE"
  },
  "fs-extra@4.0.2": {
    "licenses": "MIT",
    "repository": "https://github.com/jprichardson/node-fs-extra",
    "publisher": "JP Richardson",
    "email": "jprichardson@gmail.com",
    "licenseFile": "node_modules/builder-util-runtime/node_modules/fs-extra/LICENSE"
  },
  "ftp@0.3.10": {
    "licenses": "MIT",
    "repository": "https://github.com/mscdex/node-ftp",
    "publisher": "Brian White",
    "email": "mscdex@mscdex.net",
    "licenseFile": "node_modules/ftp/LICENSE"
  },
  "fuse.js@3.0.5": {
    "licenses": "Apache*",
    "repository": "https://github.com/krisk/Fuse",
    "publisher": "Kirollos Risk",
    "email": "kirollos@gmail.com",
    "url": "http://kiro.me",
    "licenseFile": "node_modules/fuse.js/LICENSE"
  },
  "get-uri@2.0.1": {
    "licenses": "MIT",
    "repository": "https://github.com/TooTallNate/node-get-uri",
    "publisher": "Nathan Rajlich",
    "email": "nathan@tootallnate.net",
    "url": "http://n8.io/",
    "licenseFile": "node_modules/get-uri/README.md"
  },
  "getpass@0.1.7": {
    "licenses": "MIT",
    "repository": "https://github.com/arekinath/node-getpass",
    "publisher": "Alex Wilson",
    "email": "alex.wilson@joyent.com",
    "licenseFile": "node_modules/getpass/LICENSE"
  },
  "graceful-fs@4.1.11": {
    "licenses": "ISC",
    "repository": "https://github.com/isaacs/node-graceful-fs",
    "licenseFile": "node_modules/graceful-fs/LICENSE"
  },
  "har-schema@1.0.5": {
    "licenses": "ISC",
    "repository": "https://github.com/ahmadnassri/har-schema",
    "publisher": "Ahmad Nassri",
    "email": "ahmad@ahmadnassri.com",
    "url": "https://www.ahmadnassri.com/",
    "licenseFile": "node_modules/har-schema/LICENSE"
  },
  "har-validator@4.2.1": {
    "licenses": "ISC",
    "repository": "https://github.com/ahmadnassri/har-validator",
    "publisher": "Ahmad Nassri",
    "email": "ahmad@ahmadnassri.com",
    "url": "https://www.ahmadnassri.com/",
    "licenseFile": "node_modules/har-validator/LICENSE"
  },
  "hawk@3.1.3": {
    "licenses": "BSD-3-Clause",
    "repository": "https://github.com/hueniverse/hawk",
    "publisher": "Eran Hammer",
    "email": "eran@hammer.io",
    "url": "http://hueniverse.com",
    "licenseFile": "node_modules/hawk/LICENSE"
  },
  "highlight.js@9.12.0": {
    "licenses": "BSD-3-Clause",
    "repository": "https://github.com/isagalaev/highlight.js",
    "publisher": "Ivan Sagalaev",
    "email": "maniac@softwaremaniacs.org",
    "licenseFile": "node_modules/highlight.js/LICENSE"
  },
  "hoek@2.16.3": {
    "licenses": "BSD-3-Clause",
    "repository": "https://github.com/hapijs/hoek",
    "licenseFile": "node_modules/hoek/LICENSE"
  },
  "hoist-non-react-statics@2.2.2": {
    "licenses": "BSD-3-Clause",
    "repository": "https://github.com/mridgway/hoist-non-react-statics",
    "publisher": "Michael Ridgway",
    "email": "mcridgway@gmail.com",
    "licenseFile": "node_modules/react-redux/node_modules/hoist-non-react-statics/LICENSE.md"
  },
  "hoist-non-react-statics@2.3.1": {
    "licenses": "BSD-3-Clause",
    "repository": "https://github.com/mridgway/hoist-non-react-statics",
    "publisher": "Michael Ridgway",
    "email": "mcridgway@gmail.com",
    "licenseFile": "node_modules/redux-form/node_modules/hoist-non-react-statics/LICENSE.md"
  },
  "http-errors@1.6.1": {
    "licenses": "MIT",
    "repository": "https://github.com/jshttp/http-errors",
    "publisher": "Jonathan Ong",
    "email": "me@jongleberry.com",
    "url": "http://jongleberry.com",
    "licenseFile": "node_modules/http-errors/LICENSE"
  },
  "http-proxy-agent@1.0.0": {
    "licenses": "MIT",
    "repository": "https://github.com/TooTallNate/node-http-proxy-agent",
    "publisher": "Nathan Rajlich",
    "email": "nathan@tootallnate.net",
    "url": "http://n8.io/",
    "licenseFile": "node_modules/http-proxy-agent/README.md"
  },
  "http-signature@1.1.1": {
    "licenses": "MIT",
    "repository": "https://github.com/joyent/node-http-signature",
    "publisher": "Joyent, Inc",
    "licenseFile": "node_modules/http-signature/LICENSE"
  },
  "https-proxy-agent@1.0.0": {
    "licenses": "MIT",
    "repository": "https://github.com/TooTallNate/node-https-proxy-agent",
    "publisher": "Nathan Rajlich",
    "email": "nathan@tootallnate.net",
    "url": "http://n8.io/",
    "licenseFile": "node_modules/https-proxy-agent/README.md"
  },
  "human-readable-time@0.3.0": {
    "licenses": "MIT",
    "repository": "https://github.com/g07cha/human-readable-time",
    "publisher": "G07cha",
    "licenseFile": "node_modules/human-readable-time/license"
  },
  "hyphenate-style-name@1.0.2": {
    "licenses": "BSD-3-Clause",
    "repository": "https://github.com/rexxars/hyphenate-style-name",
    "publisher": "Espen Hovlandsdal",
    "email": "espen@hovlandsdal.com",
    "licenseFile": "node_modules/hyphenate-style-name/LICENSE"
  },
  "iconv-lite@0.4.18": {
    "licenses": "MIT",
    "repository": "https://github.com/ashtuchkin/iconv-lite",
    "publisher": "Alexander Shtuchkin",
    "email": "ashtuchkin@gmail.com",
    "licenseFile": "node_modules/iconv-lite/LICENSE"
  },
  "image-downloader@3.2.2": {
    "licenses": "MIT",
    "repository": "https://github.com/demsking/image-downloader",
    "publisher": "Sébastien Demanou",
    "licenseFile": "node_modules/image-downloader/LICENSE"
  },
  "inherits@2.0.3": {
    "licenses": "ISC",
    "repository": "https://github.com/isaacs/inherits",
    "licenseFile": "node_modules/inherits/LICENSE"
  },
  "ini@1.3.4": {
    "licenses": "ISC",
    "repository": "https://github.com/isaacs/ini",
    "publisher": "Isaac Z. Schlueter",
    "email": "i@izs.me",
    "url": "http://blog.izs.me/",
    "licenseFile": "node_modules/ini/LICENSE"
  },
  "inline-style-prefixer@3.0.7": {
    "licenses": "MIT",
    "repository": "https://github.com/rofrischmann/inline-style-prefixer",
    "publisher": "Robin Frischmann",
    "licenseFile": "node_modules/inline-style-prefixer/LICENSE"
  },
  "invariant@2.2.2": {
    "licenses": "BSD-3-Clause",
    "repository": "https://github.com/zertosh/invariant",
    "publisher": "Andres Suarez",
    "email": "zertosh@gmail.com",
    "licenseFile": "node_modules/invariant/LICENSE"
  },
  "invert-kv@1.0.0": {
    "licenses": "MIT",
    "repository": "https://github.com/sindresorhus/invert-kv",
    "publisher": "Sindre Sorhus",
    "email": "sindresorhus@gmail.com",
    "url": "http://sindresorhus.com",
    "licenseFile": "node_modules/invert-kv/readme.md"
  },
  "ip@1.1.5": {
    "licenses": "MIT",
    "repository": "https://github.com/indutny/node-ip",
    "publisher": "Fedor Indutny",
    "email": "fedor@indutny.com",
    "licenseFile": "node_modules/ip/README.md"
  },
  "is-fullwidth-code-point@1.0.0": {
    "licenses": "MIT",
    "repository": "https://github.com/sindresorhus/is-fullwidth-code-point",
    "publisher": "Sindre Sorhus",
    "email": "sindresorhus@gmail.com",
    "url": "sindresorhus.com",
    "licenseFile": "node_modules/is-fullwidth-code-point/license"
  },
  "is-promise@2.1.0": {
    "licenses": "MIT",
    "repository": "https://github.com/then/is-promise",
    "publisher": "ForbesLindesay",
    "licenseFile": "node_modules/is-promise/LICENSE"
  },
  "is-stream@1.1.0": {
    "licenses": "MIT",
    "repository": "https://github.com/sindresorhus/is-stream",
    "publisher": "Sindre Sorhus",
    "email": "sindresorhus@gmail.com",
    "url": "sindresorhus.com",
    "licenseFile": "node_modules/is-stream/license"
  },
  "is-typedarray@1.0.0": {
    "licenses": "MIT",
    "repository": "https://github.com/hughsk/is-typedarray",
    "publisher": "Hugh Kennedy",
    "email": "hughskennedy@gmail.com",
    "url": "http://hughsk.io/",
    "licenseFile": "node_modules/is-typedarray/LICENSE.md"
  },
  "isarray@0.0.1": {
    "licenses": "MIT",
    "repository": "https://github.com/juliangruber/isarray",
    "publisher": "Julian Gruber",
    "email": "mail@juliangruber.com",
    "url": "http://juliangruber.com",
    "licenseFile": "node_modules/isarray/README.md"
  },
  "isarray@1.0.0": {
    "licenses": "MIT",
    "repository": "https://github.com/juliangruber/isarray",
    "publisher": "Julian Gruber",
    "email": "mail@juliangruber.com",
    "url": "http://juliangruber.com",
    "licenseFile": "node_modules/get-uri/node_modules/isarray/README.md"
  },
  "isomorphic-fetch@2.2.1": {
    "licenses": "MIT",
    "repository": "https://github.com/matthew-andrews/isomorphic-fetch",
    "publisher": "Matt Andrews",
    "email": "matt@mattandre.ws",
    "licenseFile": "node_modules/isomorphic-fetch/LICENSE"
  },
  "isstream@0.1.2": {
    "licenses": "MIT",
    "repository": "https://github.com/rvagg/isstream",
    "publisher": "Rod Vagg",
    "email": "rod@vagg.org",
    "licenseFile": "node_modules/isstream/LICENSE.md"
  },
  "js-tokens@3.0.2": {
    "licenses": "MIT",
    "repository": "https://github.com/lydell/js-tokens",
    "publisher": "Simon Lydell",
    "licenseFile": "node_modules/js-tokens/LICENSE"
  },
  "js-yaml@3.10.0": {
    "licenses": "MIT",
    "repository": "https://github.com/nodeca/js-yaml",
    "publisher": "Vladimir Zapparov",
    "email": "dervus.grim@gmail.com",
    "licenseFile": "node_modules/electron-updater/node_modules/js-yaml/LICENSE"
  },
  "jsbn@0.1.1": {
    "licenses": "MIT",
    "repository": "https://github.com/andyperlitch/jsbn",
    "publisher": "Tom Wu",
    "licenseFile": "node_modules/jsbn/LICENSE"
  },
  "json-schema@0.2.3": {
    "licenses": [
      "AFLv2.1",
      "BSD"
    ],
    "repository": "https://github.com/kriszyp/json-schema",
    "publisher": "Kris Zyp",
    "licenseFile": "node_modules/json-schema/README.md"
  },
  "json-stable-stringify@1.0.1": {
    "licenses": "MIT",
    "repository": "https://github.com/substack/json-stable-stringify",
    "publisher": "James Halliday",
    "email": "mail@substack.net",
    "url": "http://substack.net",
    "licenseFile": "node_modules/json-stable-stringify/LICENSE"
  },
  "json-stringify-safe@5.0.1": {
    "licenses": "ISC",
    "repository": "https://github.com/isaacs/json-stringify-safe",
    "publisher": "Isaac Z. Schlueter",
    "email": "i@izs.me",
    "url": "http://blog.izs.me",
    "licenseFile": "node_modules/json-stringify-safe/LICENSE"
  },
  "jsonfile@2.4.0": {
    "licenses": "MIT",
    "repository": "https://github.com/jprichardson/node-jsonfile",
    "publisher": "JP Richardson",
    "email": "jprichardson@gmail.com",
    "licenseFile": "node_modules/electron-window-state/node_modules/jsonfile/LICENSE"
  },
  "jsonfile@4.0.0": {
    "licenses": "MIT",
    "repository": "https://github.com/jprichardson/node-jsonfile",
    "publisher": "JP Richardson",
    "email": "jprichardson@gmail.com",
    "licenseFile": "node_modules/builder-util-runtime/node_modules/jsonfile/LICENSE"
  },
  "jsonify@0.0.0": {
    "licenses": "Public Domain",
    "repository": "https://github.com/substack/jsonify",
    "publisher": "Douglas Crockford",
    "url": "http://crockford.com/",
    "licenseFile": "node_modules/jsonify/README.markdown"
  },
  "jsprim@1.4.0": {
    "licenses": "MIT",
    "repository": "https://github.com/joyent/node-jsprim",
    "licenseFile": "node_modules/jsprim/LICENSE"
  },
  "keyboardevent-from-electron-accelerator@0.7.1": {
    "licenses": "MIT",
    "repository": "https://github.com/parro-it/keyboardevent-from-electron-accelerator",
    "publisher": "Andrea",
    "email": "andrea@parro.it",
    "licenseFile": "node_modules/keyboardevent-from-electron-accelerator/license"
  },
  "keyboardevents-areequal@0.2.2": {
    "licenses": "MIT",
    "repository": "https://github.com/parro-it/keyboardevents-areequal",
    "publisher": "Andrea",
    "email": "andrea@parro.it",
    "licenseFile": "node_modules/keyboardevents-areequal/license"
  },
  "keycode@2.1.9": {
    "licenses": "MIT",
    "repository": "https://github.com/timoxley/keycode",
    "publisher": "Tim Oxley",
    "email": "secoif@gmail.com",
    "licenseFile": "node_modules/keycode/LICENSE"
  },
  "lazy-val@1.0.2": {
    "licenses": "MIT",
    "repository": "https://github.com/develar/read-config-file",
    "publisher": "Vladimir Krivosheev",
    "licenseFile": "node_modules/lazy-val/readme.md"
  },
  "lcid@1.0.0": {
    "licenses": "MIT",
    "repository": "https://github.com/sindresorhus/lcid",
    "publisher": "Sindre Sorhus",
    "email": "sindresorhus@gmail.com",
    "url": "sindresorhus.com",
    "licenseFile": "node_modules/lcid/license"
  },
  "levn@0.3.0": {
    "licenses": "MIT",
    "repository": "https://github.com/gkz/levn",
    "publisher": "George Zahariev",
    "email": "z@georgezahariev.com",
    "licenseFile": "node_modules/levn/LICENSE"
  },
  "linkify-it@2.0.3": {
    "licenses": "MIT",
    "repository": "https://github.com/markdown-it/linkify-it",
    "licenseFile": "node_modules/linkify-it/LICENSE"
  },
  "lodash-es@4.17.4": {
    "licenses": "MIT",
    "repository": "https://github.com/lodash/lodash",
    "publisher": "John-David Dalton",
    "email": "john.david.dalton@gmail.com",
    "url": "http://allyoucanleet.com/",
    "licenseFile": "node_modules/lodash-es/LICENSE"
  },
  "lodash.debounce@4.0.8": {
    "licenses": "MIT",
    "repository": "https://github.com/lodash/lodash",
    "publisher": "John-David Dalton",
    "email": "john.david.dalton@gmail.com",
    "url": "http://allyoucanleet.com/",
    "licenseFile": "node_modules/lodash.debounce/LICENSE"
  },
  "lodash.isequal@4.5.0": {
    "licenses": "MIT",
    "repository": "https://github.com/lodash/lodash",
    "publisher": "John-David Dalton",
    "email": "john.david.dalton@gmail.com",
    "url": "http://allyoucanleet.com/",
    "licenseFile": "node_modules/lodash.isequal/LICENSE"
  },
  "lodash@4.17.4": {
    "licenses": "MIT",
    "repository": "https://github.com/lodash/lodash",
    "publisher": "John-David Dalton",
    "email": "john.david.dalton@gmail.com",
    "url": "http://allyoucanleet.com/",
    "licenseFile": "node_modules/lodash/LICENSE"
  },
  "loose-envify@1.3.1": {
    "licenses": "MIT",
    "repository": "https://github.com/zertosh/loose-envify",
    "publisher": "Andres Suarez",
    "email": "zertosh@gmail.com",
    "licenseFile": "node_modules/loose-envify/LICENSE"
  },
  "lru-cache@2.6.5": {
    "licenses": "ISC",
    "repository": "https://github.com/isaacs/node-lru-cache",
    "publisher": "Isaac Z. Schlueter",
    "email": "i@izs.me",
    "licenseFile": "node_modules/proxy-agent/node_modules/lru-cache/LICENSE"
  },
  "markdown-it-task-lists@2.0.1": {
    "licenses": "ISC",
    "repository": "https://github.com/revin/markdown-it-task-lists",
    "publisher": "Revin Guillen",
    "licenseFile": "node_modules/markdown-it-task-lists/LICENSE"
  },
  "markdown-it@8.3.2": {
    "licenses": "MIT",
    "repository": "https://github.com/markdown-it/markdown-it",
    "licenseFile": "node_modules/markdown-it/LICENSE"
  },
  "mdurl@1.0.1": {
    "licenses": "MIT",
    "repository": "https://github.com/markdown-it/mdurl",
    "licenseFile": "node_modules/mdurl/LICENSE"
  },
  "mime-db@1.27.0": {
    "licenses": "MIT",
    "repository": "https://github.com/jshttp/mime-db",
    "licenseFile": "node_modules/mime-db/LICENSE"
  },
  "mime-types@2.1.15": {
    "licenses": "MIT",
    "repository": "https://github.com/jshttp/mime-types",
    "licenseFile": "node_modules/mime-types/LICENSE"
  },
  "minimist@0.0.8": {
    "licenses": "MIT",
    "repository": "https://github.com/substack/minimist",
    "publisher": "James Halliday",
    "email": "mail@substack.net",
    "url": "http://substack.net",
    "licenseFile": "node_modules/minimist/LICENSE"
  },
  "mkdirp@0.5.1": {
    "licenses": "MIT",
    "repository": "https://github.com/substack/node-mkdirp",
    "publisher": "James Halliday",
    "email": "mail@substack.net",
    "url": "http://substack.net",
    "licenseFile": "node_modules/mkdirp/LICENSE"
  },
  "modify-filename@1.1.0": {
    "licenses": "MIT",
    "repository": "https://github.com/sindresorhus/modify-filename",
    "publisher": "Sindre Sorhus",
    "email": "sindresorhus@gmail.com",
    "url": "sindresorhus.com",
    "licenseFile": "node_modules/modify-filename/license"
  },
  "moment@2.18.1": {
    "licenses": "MIT",
    "repository": "https://github.com/moment/moment",
    "publisher": "Iskren Ivov Chernev",
    "email": "iskren.chernev@gmail.com",
    "url": "https://github.com/ichernev",
    "licenseFile": "node_modules/moment/LICENSE"
  },
  "ms@2.0.0": {
    "licenses": "MIT",
    "repository": "https://github.com/zeit/ms",
    "licenseFile": "node_modules/ms/license.md"
  },
  "nconf@0.8.4": {
    "licenses": "MIT",
    "repository": "https://github.com/flatiron/nconf",
    "publisher": "Charlie Robbins",
    "email": "charlie.robbins@gmail.com",
    "licenseFile": "node_modules/nconf/LICENSE"
  },
  "netmask@1.0.6": {
    "licenses": "MIT",
    "repository": "https://github.com/rs/node-netmask",
    "publisher": "Olivier Poitrey",
    "email": "rs@dailymotion.com",
    "licenseFile": "node_modules/netmask/README.md"
  },
  "node-fetch@1.7.1": {
    "licenses": "MIT",
    "repository": "https://github.com/bitinn/node-fetch",
    "publisher": "David Frank",
    "licenseFile": "node_modules/node-fetch/LICENSE.md"
  },
  "number-is-nan@1.0.1": {
    "licenses": "MIT",
    "repository": "https://github.com/sindresorhus/number-is-nan",
    "publisher": "Sindre Sorhus",
    "email": "sindresorhus@gmail.com",
    "url": "sindresorhus.com",
    "licenseFile": "node_modules/number-is-nan/license"
  },
  "oauth-sign@0.8.2": {
    "licenses": "Apache-2.0",
    "repository": "https://github.com/mikeal/oauth-sign",
    "publisher": "Mikeal Rogers",
    "email": "mikeal.rogers@gmail.com",
    "url": "http://www.futurealoof.com",
    "licenseFile": "node_modules/oauth-sign/LICENSE"
  },
  "object-assign@4.1.1": {
    "licenses": "MIT",
    "repository": "https://github.com/sindresorhus/object-assign",
    "publisher": "Sindre Sorhus",
    "email": "sindresorhus@gmail.com",
    "url": "sindresorhus.com",
    "licenseFile": "node_modules/object-assign/license"
  },
  "optionator@0.8.2": {
    "licenses": "MIT",
    "repository": "https://github.com/gkz/optionator",
    "publisher": "George Zahariev",
    "email": "z@georgezahariev.com",
    "licenseFile": "node_modules/optionator/LICENSE"
  },
  "os-locale@1.4.0": {
    "licenses": "MIT",
    "repository": "https://github.com/sindresorhus/os-locale",
    "publisher": "Sindre Sorhus",
    "email": "sindresorhus@gmail.com",
    "url": "sindresorhus.com",
    "licenseFile": "node_modules/nconf/node_modules/os-locale/license"
  },
  "pac-proxy-agent@2.0.0": {
    "licenses": "MIT",
    "repository": "https://github.com/TooTallNate/node-pac-proxy-agent",
    "publisher": "Nathan Rajlich",
    "email": "nathan@tootallnate.net",
    "url": "http://n8.io/",
    "licenseFile": "node_modules/pac-proxy-agent/README.md"
  },
  "pac-resolver@3.0.0": {
    "licenses": "MIT",
    "repository": "https://github.com/TooTallNate/node-pac-resolver",
    "publisher": "Nathan Rajlich",
    "email": "nathan@tootallnate.net",
    "url": "http://n8.io/",
    "licenseFile": "node_modules/pac-resolver/README.md"
  },
  "path-exists@3.0.0": {
    "licenses": "MIT",
    "repository": "https://github.com/sindresorhus/path-exists",
    "publisher": "Sindre Sorhus",
    "email": "sindresorhus@gmail.com",
    "url": "sindresorhus.com",
    "licenseFile": "node_modules/path-exists/license"
  },
  "performance-now@0.2.0": {
    "licenses": "MIT",
    "repository": "https://github.com/meryn/performance-now",
    "publisher": "Meryn Stol",
    "email": "merynstol@gmail.com",
    "licenseFile": "node_modules/performance-now/license.txt"
  },
  "prelude-ls@1.1.2": {
    "licenses": "MIT",
    "repository": "https://github.com/gkz/prelude-ls",
    "publisher": "George Zahariev",
    "email": "z@georgezahariev.com",
    "licenseFile": "node_modules/prelude-ls/LICENSE"
  },
  "process-nextick-args@1.0.7": {
    "licenses": "MIT",
    "repository": "https://github.com/calvinmetcalf/process-nextick-args",
    "licenseFile": "node_modules/process-nextick-args/license.md"
  },
  "promise@7.3.1": {
    "licenses": "MIT",
    "repository": "https://github.com/then/promise",
    "publisher": "ForbesLindesay",
    "licenseFile": "node_modules/promise/LICENSE"
  },
  "prop-types-extra@1.0.1": {
    "licenses": "MIT",
    "repository": "https://github.com/react-bootstrap/react-prop-types",
    "publisher": "Matthew L Smith",
    "email": "mtscout6@gmail.com",
    "licenseFile": "node_modules/prop-types-extra/LICENSE"
  },
  "prop-types@15.5.10": {
    "licenses": "BSD-3-Clause",
    "repository": "https://github.com/reactjs/prop-types",
    "licenseFile": "node_modules/prop-types/LICENSE"
  },
  "proxy-agent@2.1.0": {
    "licenses": "MIT",
    "repository": "https://github.com/TooTallNate/node-proxy-agent",
    "publisher": "Nathan Rajlich",
    "email": "nathan@tootallnate.net",
    "url": "http://n8.io/",
    "licenseFile": "node_modules/proxy-agent/README.md"
  },
  "punycode@1.4.1": {
    "licenses": "MIT",
    "repository": "https://github.com/bestiejs/punycode.js",
    "publisher": "Mathias Bynens",
    "url": "https://mathiasbynens.be/",
    "licenseFile": "node_modules/punycode/README.md"
  },
  "pupa@1.0.0": {
    "licenses": "MIT",
    "repository": "https://github.com/sindresorhus/pupa",
    "publisher": "Sindre Sorhus",
    "email": "sindresorhus@gmail.com",
    "url": "sindresorhus.com",
    "licenseFile": "node_modules/pupa/license"
  },
  "qs@6.4.0": {
    "licenses": "BSD-3-Clause",
    "repository": "https://github.com/ljharb/qs",
    "licenseFile": "node_modules/qs/LICENSE"
  },
  "raw-body@2.3.0": {
    "licenses": "MIT",
    "repository": "https://github.com/stream-utils/raw-body",
    "publisher": "Jonathan Ong",
    "email": "me@jongleberry.com",
    "url": "http://jongleberry.com",
    "licenseFile": "node_modules/raw-body/LICENSE"
  },
  "react-bootstrap@0.31.2": {
    "licenses": "MIT",
    "repository": "https://github.com/react-bootstrap/react-bootstrap",
    "publisher": "Stephen J. Collings",
    "email": "stevoland@gmail.com",
    "licenseFile": "node_modules/react-bootstrap/LICENSE"
  },
  "react-codemirror@1.0.0": {
    "licenses": "MIT",
    "repository": "https://github.com/JedWatson/react-codemirror",
    "publisher": "Jed Watson",
    "licenseFile": "node_modules/react-codemirror/LICENSE"
  },
  "react-dom@15.6.1": {
    "licenses": "BSD-3-Clause",
    "repository": "https://github.com/facebook/react",
    "licenseFile": "node_modules/react-dom/LICENSE"
  },
  "react-overlays@0.7.0": {
    "licenses": "MIT",
    "repository": "https://github.com/react-bootstrap/react-overlays",
    "publisher": "Jason Quense",
    "email": "monastic.panic@gmail.com",
    "licenseFile": "node_modules/react-overlays/LICENSE"
  },
  "react-prop-types@0.4.0": {
    "licenses": "MIT",
    "repository": "https://github.com/react-bootstrap/react-prop-types",
    "publisher": "Matthew L Smith",
    "email": "mtscout6@gmail.com",
    "licenseFile": "node_modules/react-prop-types/LICENSE"
  },
  "react-redux@5.0.6": {
    "licenses": "MIT",
    "repository": "https://github.com/reactjs/react-redux",
    "publisher": "Dan Abramov",
    "email": "dan.abramov@me.com",
    "url": "http://github.com/gaearon",
    "licenseFile": "node_modules/react-redux/LICENSE.md"
  },
  "react-split-pane@0.1.66": {
    "licenses": "MIT",
    "repository": "https://github.com/tomkp/react-split-pane",
    "publisher": "tomkp",
    "email": "tom@tomkp.com",
    "licenseFile": "node_modules/react-split-pane/LICENSE"
  },
  "react-style-proptype@3.0.0": {
    "licenses": "MIT",
    "repository": "https://github.com/brigand/react-style-proptype",
    "publisher": "Frankie Bagnardi",
    "email": "f.bagnardi@gmail.com",
    "licenseFile": "node_modules/react-style-proptype/README.md"
  },
  "react@15.6.1": {
    "licenses": "BSD-3-Clause",
    "repository": "https://github.com/facebook/react",
    "licenseFile": "node_modules/react/LICENSE"
  },
  "readable-stream@1.1.14": {
    "licenses": "MIT",
    "repository": "https://github.com/isaacs/readable-stream",
    "publisher": "Isaac Z. Schlueter",
    "email": "i@izs.me",
    "url": "http://blog.izs.me/",
    "licenseFile": "node_modules/readable-stream/LICENSE"
  },
  "readable-stream@2.3.3": {
    "licenses": "MIT",
    "repository": "https://github.com/nodejs/readable-stream",
    "licenseFile": "node_modules/get-uri/node_modules/readable-stream/LICENSE"
  },
  "redux-form@7.0.4": {
    "licenses": "MIT",
    "repository": "https://github.com/erikras/redux-form",
    "publisher": "Erik Rasmussen",
    "email": "rasmussenerik@gmail.com",
    "url": "http://github.com/erikras",
    "licenseFile": "node_modules/redux-form/LICENSE"
  },
  "redux-thunk@2.2.0": {
    "licenses": "MIT",
    "repository": "https://github.com/gaearon/redux-thunk",
    "publisher": "Dan Abramov",
    "email": "dan.abramov@me.com",
    "licenseFile": "node_modules/redux-thunk/LICENSE.md"
  },
  "redux@3.7.2": {
    "licenses": "MIT",
    "repository": "https://github.com/reactjs/redux",
    "licenseFile": "node_modules/redux/LICENSE.md"
  },
  "regenerator-runtime@0.10.5": {
    "licenses": "MIT",
    "repository": "https://github.com/facebook/regenerator/tree/master/packages/regenerator-runtime",
    "publisher": "Ben Newman",
    "email": "bn@cs.stanford.edu",
    "licenseFile": "node_modules/regenerator-runtime/README.md"
  },
  "request-promise-core@1.1.1": {
    "licenses": "ISC",
    "repository": "https://github.com/request/promise-core",
    "publisher": "Nicolai Kamenzky",
    "url": "https://github.com/analog-nico",
    "licenseFile": "node_modules/request-promise-core/LICENSE"
  },
  "request-promise@4.2.1": {
    "licenses": "ISC",
    "repository": "https://github.com/request/request-promise",
    "publisher": "Nicolai Kamenzky",
    "url": "https://github.com/analog-nico",
    "licenseFile": "node_modules/request-promise/LICENSE"
  },
  "request@2.81.0": {
    "licenses": "Apache-2.0",
    "repository": "https://github.com/request/request",
    "publisher": "Mikeal Rogers",
    "email": "mikeal.rogers@gmail.com",
    "licenseFile": "node_modules/request/LICENSE"
  },
  "safe-buffer@5.1.1": {
    "licenses": "MIT",
    "repository": "https://github.com/feross/safe-buffer",
    "publisher": "Feross Aboukhadijeh",
    "email": "feross@feross.org",
    "url": "http://feross.org",
    "licenseFile": "node_modules/safe-buffer/LICENSE"
  },
  "sax@1.2.4": {
    "licenses": "ISC",
    "repository": "https://github.com/isaacs/sax-js",
    "publisher": "Isaac Z. Schlueter",
    "email": "i@izs.me",
    "url": "http://blog.izs.me/",
    "licenseFile": "node_modules/sax/LICENSE"
  },
  "secure-keys@1.0.0": {
    "licenses": "MIT",
    "publisher": "Jarrett Cruger",
    "email": "jcrugzz@gmail.com",
    "licenseFile": "node_modules/secure-keys/README.md"
  },
  "semver@5.0.3": {
    "licenses": "ISC",
    "repository": "https://github.com/npm/node-semver",
    "licenseFile": "node_modules/agent-base/node_modules/semver/LICENSE"
  },
  "semver@5.4.1": {
    "licenses": "ISC",
    "repository": "https://github.com/npm/node-semver",
    "licenseFile": "node_modules/electron-updater/node_modules/semver/LICENSE"
  },
  "setimmediate@1.0.5": {
    "licenses": "MIT",
    "repository": "https://github.com/YuzuJS/setImmediate",
    "publisher": "YuzuJS",
    "licenseFile": "node_modules/setimmediate/LICENSE.txt"
  },
  "setprototypeof@1.0.3": {
    "licenses": "ISC",
    "repository": "https://github.com/wesleytodd/setprototypeof",
    "publisher": "Wes Todd",
    "licenseFile": "node_modules/setprototypeof/LICENSE"
  },
  "smart-buffer@1.1.15": {
    "licenses": "MIT",
    "repository": "https://github.com/JoshGlazebrook/smart-buffer",
    "publisher": "Josh Glazebrook",
    "licenseFile": "node_modules/smart-buffer/LICENSE"
  },
  "sntp@1.0.9": {
    "licenses": "BSD",
    "repository": "https://github.com/hueniverse/sntp",
    "publisher": "Eran Hammer",
    "email": "eran@hammer.io",
    "url": "http://hueniverse.com",
    "licenseFile": "node_modules/sntp/LICENSE"
  },
  "socks-proxy-agent@2.1.1": {
    "licenses": "MIT",
    "repository": "https://github.com/TooTallNate/node-socks-proxy-agent",
    "publisher": "Nathan Rajlich",
    "email": "nathan@tootallnate.net",
    "url": "http://n8.io/",
    "licenseFile": "node_modules/socks-proxy-agent/README.md"
  },
  "socks-proxy-agent@3.0.0": {
    "licenses": "MIT",
    "repository": "https://github.com/TooTallNate/node-socks-proxy-agent",
    "publisher": "Nathan Rajlich",
    "email": "nathan@tootallnate.net",
    "url": "http://n8.io/",
    "licenseFile": "node_modules/pac-proxy-agent/node_modules/socks-proxy-agent/README.md"
  },
  "socks@1.1.10": {
    "licenses": "MIT",
    "repository": "https://github.com/JoshGlazebrook/socks",
    "publisher": "Josh Glazebrook",
    "licenseFile": "node_modules/socks/LICENSE"
  },
  "source-map-support@0.4.18": {
    "licenses": "MIT",
    "repository": "https://github.com/evanw/node-source-map-support",
    "licenseFile": "node_modules/electron-updater/node_modules/source-map-support/LICENSE.md"
  },
  "source-map@0.2.0": {
    "licenses": "BSD",
    "repository": "https://github.com/mozilla/source-map",
    "publisher": "Nick Fitzgerald",
    "email": "nfitzgerald@mozilla.com",
    "licenseFile": "node_modules/escodegen/node_modules/source-map/LICENSE"
  },
  "source-map@0.5.6": {
    "licenses": "BSD-3-Clause",
    "repository": "https://github.com/mozilla/source-map",
    "publisher": "Nick Fitzgerald",
    "email": "nfitzgerald@mozilla.com",
    "licenseFile": "node_modules/source-map/LICENSE"
  },
  "sprintf-js@1.0.3": {
    "licenses": "BSD-3-Clause",
    "repository": "https://github.com/alexei/sprintf.js",
    "publisher": "Alexandru Marasteanu",
    "email": "hello@alexei.ro",
    "url": "http://alexei.ro/",
    "licenseFile": "node_modules/sprintf-js/LICENSE"
  },
  "sshpk@1.13.1": {
    "licenses": "MIT",
    "repository": "https://github.com/arekinath/node-sshpk",
    "publisher": "Joyent, Inc",
    "licenseFile": "node_modules/sshpk/LICENSE"
  },
  "stack-trace@0.0.10": {
    "licenses": "MIT",
    "repository": "https://github.com/felixge/node-stack-trace",
    "publisher": "Felix Geisendörfer",
    "email": "felix@debuggable.com",
    "url": "http://debuggable.com/",
    "licenseFile": "node_modules/stack-trace/License"
  },
  "statuses@1.3.1": {
    "licenses": "MIT",
    "repository": "https://github.com/jshttp/statuses",
    "licenseFile": "node_modules/statuses/LICENSE"
  },
  "stealthy-require@1.1.1": {
    "licenses": "ISC",
    "repository": "https://github.com/analog-nico/stealthy-require",
    "publisher": "Nicolai Kamenzky",
    "url": "https://github.com/analog-nico",
    "licenseFile": "node_modules/stealthy-require/LICENSE"
  },
  "string-width@1.0.2": {
    "licenses": "MIT",
    "repository": "https://github.com/sindresorhus/string-width",
    "publisher": "Sindre Sorhus",
    "email": "sindresorhus@gmail.com",
    "url": "sindresorhus.com",
    "licenseFile": "node_modules/string-width/license"
  },
  "string_decoder@0.10.31": {
    "licenses": "MIT",
    "repository": "https://github.com/rvagg/string_decoder",
    "licenseFile": "node_modules/string_decoder/LICENSE"
  },
  "string_decoder@1.0.3": {
    "licenses": "MIT",
    "repository": "https://github.com/rvagg/string_decoder",
    "licenseFile": "node_modules/get-uri/node_modules/string_decoder/LICENSE"
  },
  "stringstream@0.0.5": {
    "licenses": "MIT",
    "repository": "https://github.com/mhart/StringStream",
    "publisher": "Michael Hart",
    "email": "michael.hart.au@gmail.com",
    "url": "http://github.com/mhart",
    "licenseFile": "node_modules/stringstream/LICENSE.txt"
  },
  "strip-ansi@3.0.1": {
    "licenses": "MIT",
    "repository": "https://github.com/chalk/strip-ansi",
    "publisher": "Sindre Sorhus",
    "email": "sindresorhus@gmail.com",
    "url": "sindresorhus.com",
    "licenseFile": "node_modules/strip-ansi/license"
  },
  "symbol-observable@1.0.4": {
    "licenses": "MIT",
    "repository": "https://github.com/blesh/symbol-observable",
    "publisher": "Ben Lesh",
    "email": "ben@benlesh.com",
    "licenseFile": "node_modules/symbol-observable/license"
  },
  "thunkify@2.1.2": {
    "licenses": "MIT",
    "repository": "https://github.com/visionmedia/node-thunkify",
    "licenseFile": "node_modules/thunkify/Readme.md"
  },
  "tough-cookie@2.3.2": {
    "licenses": "BSD-3-Clause",
    "repository": "https://github.com/salesforce/tough-cookie",
    "publisher": "Jeremy Stashewsky",
    "email": "jstashewsky@salesforce.com",
    "licenseFile": "node_modules/tough-cookie/LICENSE"
  },
  "tunnel-agent@0.6.0": {
    "licenses": "Apache-2.0",
    "repository": "https://github.com/mikeal/tunnel-agent",
    "publisher": "Mikeal Rogers",
    "email": "mikeal.rogers@gmail.com",
    "url": "http://www.futurealoof.com",
    "licenseFile": "node_modules/tunnel-agent/LICENSE"
  },
  "tweetnacl@0.14.5": {
    "licenses": "Unlicense",
    "repository": "https://github.com/dchest/tweetnacl-js",
    "publisher": "TweetNaCl-js contributors",
    "licenseFile": "node_modules/tweetnacl/LICENSE"
  },
  "twitter-text@1.14.7": {
    "licenses": "Apache*",
    "repository": "https://github.com/twitter/twitter-text-js",
    "publisher": "Twitter Inc.",
    "licenseFile": "node_modules/twitter-text/LICENSE"
  },
  "type-check@0.3.2": {
    "licenses": "MIT",
    "repository": "https://github.com/gkz/type-check",
    "publisher": "George Zahariev",
    "email": "z@georgezahariev.com",
    "licenseFile": "node_modules/type-check/LICENSE"
  },
  "ua-parser-js@0.7.13": {
    "licenses": "(GPL-2.0 OR MIT)",
    "repository": "https://github.com/faisalman/ua-parser-js",
    "publisher": "Faisal Salman",
    "email": "fyzlman@gmail.com",
    "url": "http://faisalman.com",
    "licenseFile": "node_modules/ua-parser-js/readme.md"
  },
  "uc.micro@1.0.3": {
    "licenses": "WTFPL",
    "repository": "https://github.com/markdown-it/uc.micro",
    "licenseFile": "node_modules/uc.micro/README.md"
  },
  "uncontrollable@4.1.0": {
    "licenses": "MIT",
    "repository": "https://github.com/jquense/uncontrollable",
    "publisher": "Jason Quense",
    "email": "monastic.panic@gmail.com",
    "licenseFile": "node_modules/uncontrollable/README.md"
  },
  "universalify@0.1.0": {
    "licenses": "MIT",
    "repository": "https://github.com/RyanZim/universalify",
    "publisher": "Ryan Zimmerman",
    "email": "opensrc@ryanzim.com",
    "licenseFile": "node_modules/universalify/LICENSE"
  },
  "unpipe@1.0.0": {
    "licenses": "MIT",
    "repository": "https://github.com/stream-utils/unpipe",
    "publisher": "Douglas Christopher Wilson",
    "email": "doug@somethingdoug.com",
    "licenseFile": "node_modules/unpipe/LICENSE"
  },
  "unused-filename@0.1.0": {
    "licenses": "MIT",
    "repository": "https://github.com/sindresorhus/unused-filename",
    "publisher": "Sindre Sorhus",
    "email": "sindresorhus@gmail.com",
    "url": "sindresorhus.com",
    "licenseFile": "node_modules/unused-filename/license"
  },
  "util-deprecate@1.0.2": {
    "licenses": "MIT",
    "repository": "https://github.com/TooTallNate/util-deprecate",
    "publisher": "Nathan Rajlich",
    "email": "nathan@tootallnate.net",
    "url": "http://n8.io/",
    "licenseFile": "node_modules/util-deprecate/LICENSE"
  },
  "uuid@3.1.0": {
    "licenses": "MIT",
    "repository": "https://github.com/kelektiv/node-uuid",
    "licenseFile": "node_modules/uuid/LICENSE.md"
  },
  "verror@1.3.6": {
    "licenses": "MIT*",
    "repository": "https://github.com/davepacheco/node-verror",
    "licenseFile": "node_modules/verror/LICENSE"
  },
  "warning@3.0.0": {
    "licenses": "BSD-3-Clause",
    "repository": "https://github.com/BerkeleyTrue/warning",
    "publisher": "Berkeley Martinez",
    "email": "berkeley@r3dm.com",
    "url": "http://www.freecodecamp.com",
    "licenseFile": "node_modules/warning/LICENSE.md"
  },
  "whatwg-fetch@2.0.3": {
    "licenses": "MIT",
    "repository": "https://github.com/github/fetch",
    "licenseFile": "node_modules/whatwg-fetch/LICENSE"
  },
  "window-size@0.1.4": {
    "licenses": "MIT",
    "repository": "https://github.com/jonschlinkert/window-size",
    "publisher": "Jon Schlinkert",
    "url": "https://github.com/jonschlinkert",
    "licenseFile": "node_modules/nconf/node_modules/window-size/LICENSE"
  },
  "winston@2.3.1": {
    "licenses": "MIT",
    "repository": "https://github.com/winstonjs/winston",
    "publisher": "Charlie Robbins",
    "email": "charlie.robbins@gmail.com",
    "licenseFile": "node_modules/winston/LICENSE"
  },
  "wordwrap@1.0.0": {
    "licenses": "MIT",
    "repository": "https://github.com/substack/node-wordwrap",
    "publisher": "James Halliday",
    "email": "mail@substack.net",
    "url": "http://substack.net",
    "licenseFile": "node_modules/wordwrap/LICENSE"
  },
  "wrap-ansi@2.1.0": {
    "licenses": "MIT",
    "repository": "https://github.com/chalk/wrap-ansi",
    "publisher": "Sindre Sorhus",
    "email": "sindresorhus@gmail.com",
    "url": "sindresorhus.com",
    "licenseFile": "node_modules/wrap-ansi/license"
  },
  "xelement@1.0.16": {
    "licenses": "MIT",
    "repository": "https://github.com/dongariteja/xelement",
    "publisher": "Rakesh Dhandra Dharmateja Dongari",
    "email": "dongariteja@gmail.com",
    "url": "https://in.linkedin.com/in/rakeshdongari",
    "licenseFile": "node_modules/xelement/LICENSE"
  },
  "xregexp@2.0.0": {
    "licenses": "MIT",
    "repository": "https://github.com/slevithan/XRegExp",
    "publisher": "Steven Levithan",
    "email": "steves_list@hotmail.com",
    "licenseFile": "node_modules/xregexp/README.md"
  },
  "y18n@3.2.1": {
    "licenses": "ISC",
    "repository": "https://github.com/yargs/y18n",
    "publisher": "Ben Coe",
    "email": "ben@npmjs.com",
    "licenseFile": "node_modules/y18n/LICENSE"
  },
  "yargs@3.32.0": {
    "licenses": "MIT",
    "repository": "https://github.com/bcoe/yargs",
    "publisher": "Alex Ford",
    "email": "Alex.Ford@CodeTunnel.com",
    "url": "http://CodeTunnel.com",
    "licenseFile": "node_modules/nconf/node_modules/yargs/LICENSE"
  }
}

